zz.py
yueyue-1.0.dist-info/METADATA
yueyue-1.0.dist-info/WHEEL
yueyue-1.0.dist-info/top_level.txt
yueyue-1.0.dist-info/RECORD
