Metadata-Version: 2.1
Name: yueyue
Version: 1.0
Summary: 大数据3
Home-page: UNKNOWN
Author: 大数据3
Author-email: 1423135072@qq.com
License: UNKNOWN
Platform: UNKNOWN
